aw_watcher_screenshot/__init__.py
aw_watcher_screenshot-0.1.0.dist-info/METADATA
aw_watcher_screenshot-0.1.0.dist-info/WHEEL
aw_watcher_screenshot-0.1.0.dist-info/RECORD
